quickbooks_desktop/__init__.py
quickbooks_desktop/session_manager.py
quickbooks_desktop-1.0.1.dist-info/LICENSE
quickbooks_desktop-1.0.1.dist-info/METADATA
quickbooks_desktop-1.0.1.dist-info/WHEEL
quickbooks_desktop-1.0.1.dist-info/top_level.txt
quickbooks_desktop-1.0.1.dist-info/RECORD
