Metadata-Version: 2.1
Name: quickbooks-desktop
Version: 1.0.1
Summary: Initial Release
Home-page: https://github.com/selfjared1/quickbooks_desktop/releases/tag/0.1
Download-URL: https://github.com/selfjared1/quickbooks_desktop/archive/refs/tags/0.1.zip
Author: Jared Self
Author-email: jared@quickbooksgg.com
Project-URL: Bug Tracker, https://github.com/selfjared1/quickbooks_desktop/issues
Keywords: quickbooks desktop,quickbooks
Classifier: Programming Language :: Python :: 3
Classifier: License :: OSI Approved :: MIT License
Classifier: Operating System :: Microsoft :: Windows
Requires-Python: >=3.8
License-File: LICENSE
Requires-Dist: lxml
Requires-Dist: pywin32
